dailei_testPypi-3.0.dist-info/METADATA
dailei_testPypi-3.0.dist-info/RECORD
dailei_testPypi-3.0.dist-info/WHEEL
dailei_testPypi-3.0.dist-info/top_level.txt
mypackage/__init__.py
mypackage/__version__.py
mypackage/core.py
