Metadata-Version: 2.1
Name: dailei-testPypi
Version: 3.0
Summary: My short description for my project.
Home-page: https://github.com/me/myproject
Author: daley
Author-email: 47323107@qq.com
License: MIT
Platform: UNKNOWN
Classifier: License :: OSI Approved :: MIT License
Classifier: Programming Language :: Python
Classifier: Programming Language :: Python :: 3
Classifier: Programming Language :: Python :: 3.6
Classifier: Programming Language :: Python :: Implementation :: CPython
Classifier: Programming Language :: Python :: Implementation :: PyPy
Requires-Python: >=3.6.0
